filetags/Register_filetags_for_Windows_context_menu_TEMPLATE.reg
filetags/__init__.py
filetags-2025.11.16.1.dist-info/licenses/LICENSE.txt
filetags-2025.11.16.1.dist-info/METADATA
filetags-2025.11.16.1.dist-info/WHEEL
filetags-2025.11.16.1.dist-info/entry_points.txt
filetags-2025.11.16.1.dist-info/top_level.txt
filetags-2025.11.16.1.dist-info/RECORD
