Metadata-Version: 2.4
Name: filetags
Version: 2025.11.16.1
Summary: Management of simple tags within file names and retrieval methods using those tags
Home-page: https://github.com/novoid/filetags
Download-URL: https://github.com/novoid/filetags/zipball/master
Author: Karl Voit
Author-email: Karl Voit <tools@Karl-Voit.at>
License:                     GNU GENERAL PUBLIC LICENSE
Project-URL: Homepage, https://github.com/novoid/filetags
Project-URL: Repository, https://github.com/novoid/filetags
Project-URL: Issues, https://github.com/novoid/filetags/issues
Keywords: tagging,tags,file managing,file management,files,tagtrees,tagstore,tag-based navigation,tag-based filter
Classifier: Development Status :: 5 - Production/Stable
Classifier: Environment :: Console
Classifier: Intended Audience :: End Users/Desktop
Classifier: License :: OSI Approved :: GNU General Public License v3 (GPLv3)
Classifier: Operating System :: OS Independent
Classifier: Programming Language :: Python
Classifier: Programming Language :: Python :: 3
Classifier: Programming Language :: Python :: 3 :: Only
Classifier: Programming Language :: Python :: 3.10
Classifier: Programming Language :: Python :: 3.11
Classifier: Programming Language :: Python :: 3.12
Classifier: Programming Language :: Python :: 3.13
Requires-Python: >=3.10
License-File: LICENSE.txt
Requires-Dist: clint>=0.5.1
Requires-Dist: colorama>=0.4.6
Requires-Dist: pyreadline3>=3.5.4
Requires-Dist: pypiwin32; sys_platform == "win32"
Dynamic: author
Dynamic: download-url
Dynamic: home-page
Dynamic: license-file
